ProbotDB/__init__.py
ProbotDB-1.1.dist-info/METADATA
ProbotDB-1.1.dist-info/WHEEL
ProbotDB-1.1.dist-info/top_level.txt
ProbotDB-1.1.dist-info/RECORD
