Metadata-Version: 2.1
Name: ProbotDB
Version: 1.1
Summary: ProBot embed messages feature based database, :shitoh:
Home-page: https://github.com/Etherll/probot.db
Author: Etherl
Author-email: None@domain.com
License: MIT
Download-URL: https://github.com/Etherll/probot.db
Keywords: probotdb,probot,db
Platform: UNKNOWN
Classifier: Development Status :: 3 - Alpha
Classifier: Intended Audience :: Developers
Classifier: Topic :: Software Development :: Build Tools
Classifier: License :: OSI Approved :: MIT License
Requires-Dist: requests
